thecypher/__init__.py
thecypher/package_data.dat
thecypher-1.2.3.data/data/my_data/data_file
thecypher-1.2.3.dist-info/DESCRIPTION.rst
thecypher-1.2.3.dist-info/METADATA
thecypher-1.2.3.dist-info/RECORD
thecypher-1.2.3.dist-info/WHEEL
thecypher-1.2.3.dist-info/entry_points.txt
thecypher-1.2.3.dist-info/metadata.json
thecypher-1.2.3.dist-info/top_level.txt
